DataAlchemy/__init__.py
DataAlchemy/synthetic_data.py
SyntheticDataAlchemy/__init__.py
SyntheticDataAlchemy/synthetic_data.py
SyntheticDataAlchemy-0.1.0.dist-info/LICENSE
SyntheticDataAlchemy-0.1.0.dist-info/METADATA
SyntheticDataAlchemy-0.1.0.dist-info/WHEEL
SyntheticDataAlchemy-0.1.0.dist-info/top_level.txt
SyntheticDataAlchemy-0.1.0.dist-info/RECORD
