Metadata-Version: 2.1
Name: SyntheticDataAlchemy
Version: 0.1.0
Summary: A package for generating synthetic data
Home-page: https://github.com/phillip1029/DataAlchemy
Author: Phillip Peng
Author-email: ppeng08@gmail.com
Classifier: Programming Language :: Python :: 3
Classifier: License :: OSI Approved :: MIT License
Classifier: Operating System :: OS Independent
Requires-Python: >=3.6
License-File: LICENSE
Requires-Dist: pandas
Requires-Dist: numpy
Requires-Dist: scikit-learn
Requires-Dist: scipy
Requires-Dist: category-encoders
